phenonaut/__init__.py
phenonaut/__main__.py
phenonaut/errors.py
phenonaut/phenonaut.py
phenonaut/utils.py
phenonaut/workflow.py
phenonaut/data/__init__.py
phenonaut/data/dataset.py
phenonaut/data/platemap_querier.py
phenonaut/data/recipes.py
phenonaut/metrics/__init__.py
phenonaut/metrics/distances.py
phenonaut/metrics/measures.py
phenonaut/metrics/non_ds_phenotypic_metrics.py
phenonaut/metrics/performance.py
phenonaut/metrics/utils.py
phenonaut/output/__init__.py
phenonaut/output/boxplot.py
phenonaut/output/heatmap.py
phenonaut/output/pair_plot.py
phenonaut/output/ph0_pptx_template.pptx
phenonaut/output/ph0_pptx_template_desc.pptx
phenonaut/output/pptx.py
phenonaut/output/scatter.py
phenonaut/output/spreadsheet.py
phenonaut/output/visualisation_base.py
phenonaut/packaged_datasets/__init__.py
phenonaut/packaged_datasets/base.py
phenonaut/packaged_datasets/breast_cancer.py
phenonaut/packaged_datasets/cmap.py
phenonaut/packaged_datasets/iris.py
phenonaut/packaged_datasets/lincs.py
phenonaut/packaged_datasets/metadata_moa.py
phenonaut/packaged_datasets/tcga.py
phenonaut/predict/__init__.py
phenonaut/predict/optuna_functions.py
phenonaut/predict/predict_utils.py
phenonaut/predict/predictor_dataclasses.py
phenonaut/predict/profile.py
phenonaut/predict/default_predictors/__init__.py
phenonaut/predict/default_predictors/classifiers.py
phenonaut/predict/default_predictors/multiregressors.py
phenonaut/predict/default_predictors/regressors.py
phenonaut/predict/default_predictors/pytorch_models/__init__.py
phenonaut/predict/default_predictors/pytorch_models/dave.py
phenonaut/predict/default_predictors/pytorch_models/multiregressor_nn.py
phenonaut/transforms/__init__.py
phenonaut/transforms/dimensionality_reduction.py
phenonaut/transforms/generic_transformations.py
phenonaut/transforms/imputers.py
phenonaut/transforms/preparative.py
phenonaut/transforms/supervised_transformer.py
phenonaut/transforms/transformer.py
phenonaut-2.0.3.dist-info/LICENSE
phenonaut-2.0.3.dist-info/METADATA
phenonaut-2.0.3.dist-info/WHEEL
phenonaut-2.0.3.dist-info/top_level.txt
phenonaut-2.0.3.dist-info/RECORD
