Metadata-Version: 2.1
Name: phenonaut
Version: 2.0.3
Summary: A toolkit for multiomic phenotypic space exploration.
Author-email: Steven Shave <steven.x.shave@gsk.com>, Abdullah Athar <abdullah.m.athar@gsk.com>
License: 
Project-URL: Homepage, https://carragherlab.github.io/phenonaut/
Project-URL: Documentation, https://carragherlab.github.io/phenonaut/phenonaut.html
Project-URL: Repository, https://github.com/CarragherLab/phenonaut
Project-URL: Changelog, https://github.com/CarragherLab/phenonaut/blob/main/CHANGELOG.md
Classifier: Programming Language :: Python :: 3
Classifier: License :: OSI Approved :: Apache Software License
Classifier: Operating System :: OS Independent
Requires-Python: >=3.9
License-File: LICENSE
Requires-Dist: numpy ==1.25.2
Requires-Dist: pandas >=2.0.0
Requires-Dist: scikit-learn >=1.2.0
Requires-Dist: scipy >=1.7.0
Requires-Dist: torch >=2.0.1
Requires-Dist: fire >=0.5.0
Requires-Dist: tqdm >=4.48.0
Requires-Dist: openpyxl >=3.1.1
Requires-Dist: optuna >=3.1.0
Requires-Dist: h5py >=3.6.0
Requires-Dist: matplotlib >=3.7.1
Requires-Dist: seaborn >=0.12.2
Requires-Dist: tables >=3.7.0
Requires-Dist: umap-learn >=0.5.4
Requires-Dist: rbo >=0.1.2
Requires-Dist: python-pptx >=0.6
Requires-Dist: requests
Requires-Dist: mvlearn ==0.4.1
Requires-Dist: torchvision
Requires-Dist: torchaudio
Requires-Dist: numba >=0.58.0
Requires-Dist: llvmlite >=0.41.0
Requires-Dist: ipykernel
Requires-Dist: ipywidgets
Requires-Dist: tensorboard
Provides-Extra: dev
Requires-Dist: pandas ==2.1.1 ; extra == 'dev'
Requires-Dist: black ==23.3.0 ; extra == 'dev'
Requires-Dist: pytest ==7.4.0 ; extra == 'dev'
Requires-Dist: build ==0.10.0 ; extra == 'dev'
Requires-Dist: pre-commit ==3.5.0 ; extra == 'dev'
Requires-Dist: sphinx ==7.2.6 ; extra == 'dev'
Requires-Dist: sphinx-rtd-theme ; extra == 'dev'
